Exercise1/Stump_ALU.v
// Stump ALU
// Implement your Stump ALU here
//
// Created by Horia-Gabriel Radu, Oct 2020
//
// ** Update this header **

// 'include' definitions of function codes etc.
// e.g. can use "`ADD" instead of "'h0" to aid readability
// Substitute your own definitions if you prefer.
`include "../Include/Stump_definitions.v"

// for simulation purposes, do not delete
`default_nettype none


/*----------------------------------------------------------------------------*/

module Stump_ALU (input  wire [15:0] operand_A,		// First operand
                  input  wire [15:0] operand_B,		// Second operand
		          input  wire [ 2:0] func,			// Function specifier
		          input  wire        c_in,			// Carry input
		          input  wire        csh,  			// Carry from shifter
		          output reg  [15:0] result,		// ALU output
		          output reg  [ 3:0] flags_out);	// Flags {N, Z, V, C}


/* - - - - - - - - - - - - - - - - - - - - - - - - - - - - - - - - - - - - - -*/
/* Declarations of any internal signals and buses used                        */

reg C14, C15; /* Setting registers for the carry value of bit 14 and 15 */

/* - - - - - - - - - - - - - - - - - - - - - - - - - - - - - - - - - - - - - -*/

/* - - - - - - - - - - - - - - - - - - - - - - - - - - - - - - - - - - - - - -*/
/* Verilog code                                                               */

/* Executes the always block every time a signal is recieved */
always @ (*)
begin
	/* Making a case to catch each function */
	case (func)
		3'b000: /* ADD */
		begin
			result = operand_A + operand_B;
			/* Setting the flags for ADD */
			flags_out[3] = (result[15] == 1);
			flags_out[2] = (result == 16'b0000_0000_0000_0000);
			/* Calculating the Carry from bit 14 and bit 15 */
			C14 = ((operand_A[15] ^ operand_B[15]) != result[15]);
			C15 = (operand_A[15] & operand_B[15]) | (operand_A[15] & C14) | (operand_B[15] & C14);
			flags_out[1] = (C14 != C15);
			flags_out[0] = C15;
		end

		3'b001: /* ADC */
		begin
			result = operand_A + operand_B + c_in;
			/* Setting the flags for ADC */
			flags_out[3] = (result[15] == 1);
			flags_out[2] = (result == 16'b0000_0000_0000_0000);
			/* Calculating the Carry from bit 14 and bit 15 */
			C14 = ((operand_A[15] ^ operand_B[15]) != result[15]);
			C15 = (operand_A[15] & operand_B[15]) | (operand_A[15] & C14) | (operand_B[15] & C14);
			flags_out[1] = (C14 != C15);
			flags_out[0] = C15;
		end

		3'b010: /* SUB */
		begin
			result = operand_A + ~operand_B + 1;
			/* Setting the flags for SUB */
			flags_out[3] = (result[15] == 1);
			flags_out[2] = (result == 16'b0000_0000_0000_0000);
			/* Calculating the Carry from bit 14 and bit 15 */
			C14 = ((operand_A[15] ^ (~operand_B[15])) != result[15]);
			C15 = (operand_A[15] & (~operand_B[15])) | (operand_A[15] & C14) | ((~operand_B[15]) & C14);
			flags_out[1] = (C14 != C15);
			flags_out[0] = ~C15;
		end

		3'b011: /* SBC */
		begin
			result = operand_A + ~operand_B + {15'b0, ~c_in} ;
			/* Setting the flags for SBC */
			flags_out[3] = (result[15] == 1);
			flags_out[2] = (result == 16'b0000_0000_0000_0000);
			/* Calculating the Carry from bit 14 and bit 15 */
			C14 = ((operand_A[15] ^ (~operand_B[15])) != result[15]);
			C15 = (operand_A[15] & (~operand_B[15])) | (operand_A[15] & C14) | ((~operand_B[15]) & C14);
			flags_out[1] = (C14 != C15);
			flags_out[0] = ~C15;
		end

		3'b100: /* AND */
		begin
			/* Simple logic AND operator */
			result = operand_A & operand_B;
			/* Setting the flags for AND */
			flags_out[3] = (result[15] == 1);
			flags_out[2] = (result == 16'b0000_0000_0000_0000);
			flags_out[1] = 1'b0;
			flags_out[0] = csh;
		end

		3'b101: /* OR */
		begin
			/* Simple logic OR operator */
			result = operand_A | operand_B;
			/* Setting the flags for OR */
			flags_out[3] = (result[15] == 1);
			flags_out[2] = (result == 16'b0000_0000_0000_0000);
			flags_out[1] = 1'b0;
			flags_out[0] = csh;
		end

		/* Default case to catch anything that may have slipped past the other cases */
		/* The default case also catches the LD/ST */
		/* and the BCC instructions */
		default:
		begin
			result = 16'bx;
			flags_out = 4'bx;
		end
	endcase
end

/* - - - - - - - - - - - - - - - - - - - - - - - - - - - - - - - - - - - - - -*/

/*----------------------------------------------------------------------------*/

endmodule

// for simulation purposes, do not delete
`default_nettype wire

/*============================================================================*/

Exercise4/Stump_ALU_tb.v
/* Tests for Stump ALU.  Developed for COMP22111 labs.      JDG  Nov 2012     */
/*                                                                            */
/* Updated Sept 2020 by P W Nutter                                            */
/* This runs through a set of test vectors, with both input carry states for  */
/* all six ALU functions generating all possible combinations of output flags.*/

`include "../Include/Stump_definitions.v"

/*----------------------------------------------------------------------------*/

module Stump_ALU_tb ();                   // Declare the test module: no I/O

reg  [15:0] operand_A;                    // Declare the variables at this level
reg  [15:0] operand_B;                    // 'reg' for values test assigns to
reg   [2:0] func;                         // (i.e. inputs to device)
reg         c_in;
reg         csh;
wire [15:0] result;                       // 'wire' for device's output values
wire  [3:0] flags_out;

/* - - - - - - - - - - - - - - - - - - - - - - - - - - - - - - - - - - - - - -*/

Stump_ALU ALU (.operand_A(operand_A),     // Instantiate a 'Stump_ALU'
               .operand_B(operand_B),     // called 'ALU'
	           .func(func),               // and connect its buses
	           .c_in(c_in),               // to signals of the same name
               .csh(csh),
	           .result(result),
	           .flags_out(flags_out));

/* - - - - - - - - - - - - - - - - - - - - - - - - - - - - - - - - - - - - - -*/

integer file_handle;                      // The place to write output
integer tst, k;                           // Some internal variables

reg [15:0] A_in [0:8];                    // Small RAMs to hold test values
reg [15:0] B_in [0:8];

/* - - - - - - - - - - - - - - - - - - - - - - - - - - - - - - - - - - - - - -*/

initial                                   // Run the following once
begin

// Setup test data here rather than reading from files: easier for small sets
A_in[0] = 16'h4000; B_in[0] = 16'h3FFF;   // Data for test #0
A_in[1] = 16'h5000; B_in[1] = 16'h5000;   // etc.
A_in[2] = 16'h4000; B_in[2] = 16'hBFFF;
A_in[3] = 16'h4000; B_in[3] = 16'hD000;
A_in[4] = 16'hC000; B_in[4] = 16'h4000;
A_in[5] = 16'hD000; B_in[5] = 16'h2FFF;
A_in[6] = 16'hC000; B_in[6] = 16'h9000;
A_in[7] = 16'hC000; B_in[7] = 16'hBFFF;
A_in[8] = 16'h8000; B_in[8] = 16'h8000;

file_handle = $fopen("ALU_test_out.txt"); // Open a message output file
$fdisplay(file_handle, "Outcome from Stump ALU tests\n"); // Output title

for (func = 0; func < 6; func = func + 1) // Iterate over six function types
  begin
  case (func)
    0: $fdisplay(file_handle, "Testing ADD function");
    1: $fdisplay(file_handle, "Testing ADC function");
    2: $fdisplay(file_handle, "Testing SUB function");
    3: $fdisplay(file_handle, "Testing SBC function");
    4: $fdisplay(file_handle, "Testing AND function");
    5: $fdisplay(file_handle, "Testing OR  function");
    default: $fdisplay(file_handle, "Unknown function");
  endcase
  for (tst = 0; tst < 9; tst = tst + 1)   // Iterate over test data
    begin
    operand_A = A_in[tst];                // Set input buses
    operand_B = B_in[tst];
    for (k = 0; k < 2; k = k + 1)         // Iterate over (both) carry states
      begin
       if(func < 4)
        c_in = k;                         // Carry adopts LSB
       else
        csh = k;
      #100                                // Pause so viewable as waveform
      display_state(result, flags_out);   // Write results to output file
      end
    end

  $fdisplay(file_handle, "");             // Blank line after each test block
  end

#100;                                     // Extra pause before finishing

$fclose(file_handle);                     // Close output file

$finish;                                    // Tell simulator to stop
end 

// Save results as VCD file 
initial
 begin
  $dumpfile("Stump_ALU_results.vcd");
  $dumpvars;
 end
 
/* - - - - - - - - - - - - - - - - - - - - - - - - - - - - - - - - - - - - - -*/
/* Example of a 'task' (a bit like a 'method')                                */

task display_state;                       // Task declaration and name
input [15:0] result;                      // Inputs in the appropriate order
input  [3:0] flags;                       // (Outputs (many) are also possible)

case (flags)
  'h0: $fdisplay(file_handle, "Output state: %x  ....", result);
  'h1: $fdisplay(file_handle, "Output state: %x  ...C", result);
  'h2: $fdisplay(file_handle, "Output state: %x  ..V.", result);
  'h3: $fdisplay(file_handle, "Output state: %x  ..VC", result);
  'h4: $fdisplay(file_handle, "Output state: %x  .Z..", result);
  'h5: $fdisplay(file_handle, "Output state: %x  .Z.C", result);
  'h6: $fdisplay(file_handle, "Output state: %x  .ZV.", result);
  'h7: $fdisplay(file_handle, "Output state: %x  .ZVC", result);
  'h8: $fdisplay(file_handle, "Output state: %x  N...", result);
  'h9: $fdisplay(file_handle, "Output state: %x  N..C", result);
  'hA: $fdisplay(file_handle, "Output state: %x  N.V.", result);
  'hB: $fdisplay(file_handle, "Output state: %x  N.VC", result);
  'hC: $fdisplay(file_handle, "Output state: %x  NZ..", result);
  'hD: $fdisplay(file_handle, "Output state: %x  NZ.C", result);
  'hE: $fdisplay(file_handle, "Output state: %x  NZV.", result);
  'hF: $fdisplay(file_handle, "Output state: %x  NZVC", result);
  default:
       $fdisplay(file_handle, "Output state: %x  ????", result);
endcase

endtask

/* - - - - - - - - - - - - - - - - - - - - - - - - - - - - - - - - - - - - - -*/

endmodule

/*----------------------------------------------------------------------------*/

Exercise4/Stump_ALU_results.vcd
$date
	Wed Oct 28 14:11:35 2020
$end
$version
	Icarus Verilog
$end
$timescale
	1s
$end
$scope module Stump_ALU_tb $end
$var wire 16 ! result [15:0] $end
$var wire 4 " flags_out [3:0] $end
$var reg 1 # c_in $end
$var reg 1 $ csh $end
$var reg 3 % func [2:0] $end
$var reg 16 & operand_A [15:0] $end
$var reg 16 ' operand_B [15:0] $end
$var integer 32 ( file_handle [31:0] $end
$var integer 32 ) k [31:0] $end
$var integer 32 * tst [31:0] $end
$scope module ALU $end
$var wire 1 # c_in $end
$var wire 1 $ csh $end
$var wire 3 + func [2:0] $end
$var wire 16 , operand_A [15:0] $end
$var wire 16 - operand_B [15:0] $end
$var reg 1 . C14 $end
$var reg 1 / C15 $end
$var reg 4 0 flags_out [3:0] $end
$var reg 16 1 result [15:0] $end
$upscope $end
$scope task display_state $end
$var reg 4 2 flags [3:0] $end
$var reg 16 3 result [15:0] $end
$upscope $end
$upscope $end
$enddefinitions $end
#0
$dumpvars
bx 3
bx 2
b111111111111111 1
b0 0
0/
0.
b11111111111111 -
b100000000000000 ,
b0 +
b0 *
b0 )
b10 (
b11111111111111 '
b100000000000000 &
b0 %
x$
0#
b0 "
b111111111111111 !
$end
#100
1#
b1 )
b0 2
b111111111111111 3
#200
1.
b1010 "
b1010 0
b1010000000000000 !
b1010000000000000 1
0#
b101000000000000 '
b101000000000000 -
b101000000000000 &
b101000000000000 ,
b1 *
b0 )
#300
1#
b1 )
b1010 2
b1010000000000000 3
#400
b1000 "
b1000 0
0.
b1111111111111111 !
b1111111111111111 1
0#
b1011111111111111 '
b1011111111111111 -
b100000000000000 &
b100000000000000 ,
b10 *
b0 )
#500
1#
b1 )
b1000 2
b1111111111111111 3
#600
1/
1.
b1 "
b1 0
b1000000000000 !
b1000000000000 1
0#
b1101000000000000 '
b1101000000000000 -
b11 *
b0 )
#700
1#
b1 )
b1 2
b1000000000000 3
#800
b101 "
b101 0
b0 !
b0 1
0#
b100000000000000 '
b100000000000000 -
b1100000000000000 &
b1100000000000000 ,
b100 *
b0 )
#900
1#
b1 )
b101 2
b0 3
#1000
0/
0.
b1000 "
b1000 0
b1111111111111111 !
b1111111111111111 1
0#
b10111111111111 '
b10111111111111 -
b1101000000000000 &
b1101000000000000 ,
b101 *
b0 )
#1100
1#
b1 )
b1000 2
b1111111111111111 3
#1200
1/
b11 "
b11 0
b101000000000000 !
b101000000000000 1
0#
b1001000000000000 '
b1001000000000000 -
b1100000000000000 &
b1100000000000000 ,
b110 *
b0 )
#1300
1#
b1 )
b11 2
b101000000000000 3
#1400
b111111111111111 !
b111111111111111 1
0#
b1011111111111111 '
b1011111111111111 -
b111 *
b0 )
#1500
1#
b1 )
b111111111111111 3
#1600
b111 "
b111 0
b0 !
b0 1
0#
b1000000000000000 '
b1000000000000000 -
b1000000000000000 &
b1000000000000000 ,
b1000 *
b0 )
#1700
1#
b1 )
b111 2
b0 3
#1800
0/
b0 "
b0 0
b111111111111111 !
b111111111111111 1
0#
b11111111111111 '
b11111111111111 -
b100000000000000 &
b100000000000000 ,
b1 %
b1 +
b0 *
b0 )
#1900
1.
b1010 "
b1010 0
b1000000000000000 !
b1000000000000000 1
1#
b1 )
b0 2
b111111111111111 3
#2000
b1010000000000000 !
b1010000000000000 1
0#
b101000000000000 '
b101000000000000 -
b101000000000000 &
b101000000000000 ,
b1 *
b0 )
b1010 2
b1000000000000000 3
#2100
b1010000000000001 !
b1010000000000001 1
1#
b1 )
b1010000000000000 3
#2200
b1000 "
b1000 0
0.
b1111111111111111 !
b1111111111111111 1
0#
b1011111111111111 '
b1011111111111111 -
b100000000000000 &
b100000000000000 ,
b10 *
b0 )
b1010000000000001 3
#2300
1/
1.
b101 "
b101 0
b0 !
b0 1
1#
b1 )
b1000 2
b1111111111111111 3
#2400
b1 "
b1 0
b1000000000000 !
b1000000000000 1
0#
b1101000000000000 '
b1101000000000000 -
b11 *
b0 )
b101 2
b0 3
#2500
b1000000000001 !
b1000000000001 1
1#
b1 )
b1 2
b1000000000000 3
#2600
b101 "
b101 0
b0 !
b0 1
0#
b100000000000000 '
b100000000000000 -
b1100000000000000 &
b1100000000000000 ,
b100 *
b0 )
b1000000000001 3
#2700
b1 "
b1 0
b1 !
b1 1
1#
b1 )
b101 2
b0 3
#2800
0/
0.
b1000 "
b1000 0
b1111111111111111 !
b1111111111111111 1
0#
b10111111111111 '
b10111111111111 -
b1101000000000000 &
b1101000000000000 ,
b101 *
b0 )
b1 2
b1 3
#2900
1/
1.
b101 "
b101 0
b0 !
b0 1
1#
b1 )
b1000 2
b1111111111111111 3
#3000
0.
b11 "
b11 0
b101000000000000 !
b101000000000000 1
0#
b1001000000000000 '
b1001000000000000 -
b1100000000000000 &
b1100000000000000 ,
b110 *
b0 )
b101 2
b0 3
#3100
b101000000000001 !
b101000000000001 1
1#
b1 )
b11 2
b101000000000000 3
#3200
b111111111111111 !
b111111111111111 1
0#
b1011111111111111 '
b1011111111111111 -
b111 *
b0 )
b101000000000001 3
#3300
1.
b1001 "
b1001 0
b1000000000000000 !
b1000000000000000 1
1#
b1 )
b111111111111111 3
#3400
0.
b111 "
b111 0
b0 !
b0 1
0#
b1000000000000000 '
b1000000000000000 -
b1000000000000000 &
b1000000000000000 ,
b1000 *
b0 )
b1001 2
b1000000000000000 3
#3500
b11 "
b11 0
b1 !
b1 1
1#
b1 )
b111 2
b0 3
#3600
b0 "
b0 0
1.
0#
b11111111111111 '
b11111111111111 -
b100000000000000 &
b100000000000000 ,
b10 %
b10 +
b0 *
b0 )
b11 2
b1 3
#3700
1#
b1 )
b0 2
#3800
b100 "
b100 0
b0 !
b0 1
0#
b101000000000000 '
b101000000000000 -
b101000000000000 &
b101000000000000 ,
b1 *
b0 )
#3900
1#
b1 )
b100 2
b0 3
#4000
0/
b1011 "
b1011 0
b1000000000000001 !
b1000000000000001 1
0#
b1011111111111111 '
b1011111111111111 -
b100000000000000 &
b100000000000000 ,
b10 *
b0 )
#4100
1#
b1 )
b1011 2
b1000000000000001 3
#4200
0.
b1 "
b1 0
b111000000000000 !
b111000000000000 1
0#
b1101000000000000 '
b1101000000000000 -
b11 *
b0 )
#4300
1#
b1 )
b1 2
b111000000000000 3
#4400
1/
1.
b1000 "
b1000 0
b1000000000000000 !
b1000000000000000 1
0#
b100000000000000 '
b100000000000000 -
b1100000000000000 &
b1100000000000000 ,
b100 *
b0 )
#4500
1#
b1 )
b1000 2
b1000000000000000 3
#4600
b1010000000000001 !
b1010000000000001 1
0#
b10111111111111 '
b10111111111111 -
b1101000000000000 &
b1101000000000000 ,
b101 *
b0 )
#4700
1#
b1 )
b1010000000000001 3
#4800
b0 "
b0 0
b11000000000000 !
b11000000000000 1
0#
b1001000000000000 '
b1001000000000000 -
b1100000000000000 &
b1100000000000000 ,
b110 *
b0 )
#4900
1#
b1 )
b0 2
b11000000000000 3
#5000
b1 !
b1 1
0#
b1011111111111111 '
b1011111111111111 -
b111 *
b0 )
#5100
1#
b1 )
b1 3
#5200
b100 "
b100 0
b0 !
b0 1
0#
b1000000000000000 '
b1000000000000000 -
b1000000000000000 &
b1000000000000000 ,
b1000 *
b0 )
#5300
1#
b1 )
b100 2
b0 3
#5400
b0 "
b0 0
b1 !
b1 1
0#
b11111111111111 '
b11111111111111 -
b100000000000000 &
b100000000000000 ,
b11 %
b11 +
b0 *
b0 )
#5500
b100 "
b100 0
b0 !
b0 1
1#
b1 )
b0 2
b1 3
#5600
0#
b101000000000000 '
b101000000000000 -
b101000000000000 &
b101000000000000 ,
b1 *
b0 )
b100 2
b0 3
#5700
0/
0.
b1001 "
b1001 0
b1111111111111111 !
b1111111111111111 1
1#
b1 )
#5800
b1011 "
b1011 0
1.
b1000000000000001 !
b1000000000000001 1
0#
b1011111111111111 '
b1011111111111111 -
b100000000000000 &
b100000000000000 ,
b10 *
b0 )
b1001 2
b1111111111111111 3
#5900
b1000000000000000 !
b1000000000000000 1
1#
b1 )
b1011 2
b1000000000000001 3
#6000
0.
b1 "
b1 0
b111000000000000 !
b111000000000000 1
0#
b1101000000000000 '
b1101000000000000 -
b11 *
b0 )
b1000000000000000 3
#6100
b110111111111111 !
b110111111111111 1
1#
b1 )
b1 2
b111000000000000 3
#6200
1/
1.
b1000 "
b1000 0
b1000000000000000 !
b1000000000000000 1
0#
b100000000000000 '
b100000000000000 -
b1100000000000000 &
b1100000000000000 ,
b100 *
b0 )
b110111111111111 3
#6300
0.
b10 "
b10 0
b111111111111111 !
b111111111111111 1
1#
b1 )
b1000 2
b1000000000000000 3
#6400
1.
b1000 "
b1000 0
b1010000000000001 !
b1010000000000001 1
0#
b10111111111111 '
b10111111111111 -
b1101000000000000 &
b1101000000000000 ,
b101 *
b0 )
b10 2
b111111111111111 3
#6500
b1010000000000000 !
b1010000000000000 1
1#
b1 )
b1000 2
b1010000000000001 3
#6600
b0 "
b0 0
b11000000000000 !
b11000000000000 1
0#
b1001000000000000 '
b1001000000000000 -
b1100000000000000 &
b1100000000000000 ,
b110 *
b0 )
b1010000000000000 3
#6700
b10111111111111 !
b10111111111111 1
1#
b1 )
b0 2
b11000000000000 3
#6800
b1 !
b1 1
0#
b1011111111111111 '
b1011111111111111 -
b111 *
b0 )
b10111111111111 3
#6900
b100 "
b100 0
b0 !
b0 1
1#
b1 )
b1 3
#7000
0#
b1000000000000000 '
b1000000000000000 -
b1000000000000000 &
b1000000000000000 ,
b1000 *
b0 )
b100 2
b0 3
#7100
0/
0.
b1001 "
b1001 0
b1111111111111111 !
b1111111111111111 1
1#
b1 )
#7200
b100 "
b100 0
b0 !
b0 1
0$
b11111111111111 '
b11111111111111 -
b100000000000000 &
b100000000000000 ,
b100 %
b100 +
b0 *
b0 )
b1001 2
b1111111111111111 3
#7300
b101 "
b101 0
1$
b1 )
b100 2
b0 3
#7400
b0 "
b0 0
b101000000000000 !
b101000000000000 1
0$
b101000000000000 '
b101000000000000 -
b101000000000000 &
b101000000000000 ,
b1 *
b0 )
b101 2
#7500
b1 "
b1 0
1$
b1 )
b0 2
b101000000000000 3
#7600
b100 "
b100 0
b0 !
b0 1
0$
b1011111111111111 '
b1011111111111111 -
b100000000000000 &
b100000000000000 ,
b10 *
b0 )
b1 2
#7700
b101 "
b101 0
1$
b1 )
b100 2
b0 3
#7800
b0 "
b0 0
b100000000000000 !
b100000000000000 1
0$
b1101000000000000 '
b1101000000000000 -
b11 *
b0 )
b101 2
#7900
b1 "
b1 0
1$
b1 )
b0 2
b100000000000000 3
#8000
b0 "
b0 0
0$
b100000000000000 '
b100000000000000 -
b1100000000000000 &
b1100000000000000 ,
b100 *
b0 )
b1 2
#8100
b1 "
b1 0
1$
b1 )
b0 2
#8200
b100 "
b100 0
b0 !
b0 1
0$
b10111111111111 '
b10111111111111 -
b1101000000000000 &
b1101000000000000 ,
b101 *
b0 )
b1 2
#8300
b101 "
b101 0
1$
b1 )
b100 2
b0 3
#8400
b1000 "
b1000 0
b1000000000000000 !
b1000000000000000 1
0$
b1001000000000000 '
b1001000000000000 -
b1100000000000000 &
b1100000000000000 ,
b110 *
b0 )
b101 2
#8500
b1001 "
b1001 0
1$
b1 )
b1000 2
b1000000000000000 3
#8600
b1000 "
b1000 0
0$
b1011111111111111 '
b1011111111111111 -
b111 *
b0 )
b1001 2
#8700
b1001 "
b1001 0
1$
b1 )
b1000 2
#8800
b1000 "
b1000 0
0$
b1000000000000000 '
b1000000000000000 -
b1000000000000000 &
b1000000000000000 ,
b1000 *
b0 )
b1001 2
#8900
b1001 "
b1001 0
1$
b1 )
b1000 2
#9000
b0 "
b0 0
b111111111111111 !
b111111111111111 1
0$
b11111111111111 '
b11111111111111 -
b100000000000000 &
b100000000000000 ,
b101 %
b101 +
b0 *
b0 )
b1001 2
#9100
b1 "
b1 0
1$
b1 )
b0 2
b111111111111111 3
#9200
b0 "
b0 0
b101000000000000 !
b101000000000000 1
0$
b101000000000000 '
b101000000000000 -
b101000000000000 &
b101000000000000 ,
b1 *
b0 )
b1 2
#9300
b1 "
b1 0
1$
b1 )
b0 2
b101000000000000 3
#9400
b1000 "
b1000 0
b1111111111111111 !
b1111111111111111 1
0$
b1011111111111111 '
b1011111111111111 -
b100000000000000 &
b100000000000000 ,
b10 *
b0 )
b1 2
#9500
b1001 "
b1001 0
1$
b1 )
b1000 2
b1111111111111111 3
#9600
b1000 "
b1000 0
b1101000000000000 !
b1101000000000000 1
0$
b1101000000000000 '
b1101000000000000 -
b11 *
b0 )
b1001 2
#9700
b1001 "
b1001 0
1$
b1 )
b1000 2
b1101000000000000 3
#9800
b1000 "
b1000 0
b1100000000000000 !
b1100000000000000 1
0$
b100000000000000 '
b100000000000000 -
b1100000000000000 &
b1100000000000000 ,
b100 *
b0 )
b1001 2
#9900
b1001 "
b1001 0
1$
b1 )
b1000 2
b1100000000000000 3
#10000
b1000 "
b1000 0
b1111111111111111 !
b1111111111111111 1
0$
b10111111111111 '
b10111111111111 -
b1101000000000000 &
b1101000000000000 ,
b101 *
b0 )
b1001 2
#10100
b1001 "
b1001 0
1$
b1 )
b1000 2
b1111111111111111 3
#10200
b1000 "
b1000 0
b1101000000000000 !
b1101000000000000 1
0$
b1001000000000000 '
b1001000000000000 -
b1100000000000000 &
b1100000000000000 ,
b110 *
b0 )
b1001 2
#10300
b1001 "
b1001 0
1$
b1 )
b1000 2
b1101000000000000 3
#10400
b1000 "
b1000 0
b1111111111111111 !
b1111111111111111 1
0$
b1011111111111111 '
b1011111111111111 -
b111 *
b0 )
b1001 2
#10500
b1001 "
b1001 0
1$
b1 )
b1000 2
b1111111111111111 3
#10600
b1000 "
b1000 0
b1000000000000000 !
b1000000000000000 1
0$
b1000000000000000 '
b1000000000000000 -
b1000000000000000 &
b1000000000000000 ,
b1000 *
b0 )
b1001 2
#10700
b1001 "
b1001 0
1$
b1 )
b1000 2
b1000000000000000 3
#10800
bx "
bx 0
bx !
bx 1
b110 %
b110 +
b1001 *
b10 )
b1001 2
