Exercise3/Stump_FSM.v
// Stump FSM
// Implement your Stump FSM here
//
// Created by Horia-Gabriel Radu, Nov 2020
//
// ** Update this header **

// 'include' definitions of function codes etc.
`include "../Include/Stump_definitions.v"

// for simulation purposes, do not delete
`default_nettype none

module Stump_FSM (input  wire	     clk,	    // System clock
                  input  wire	     rst,	    // Master reset
                  input  wire [2:0]  opcode,    // Opcode from IR
                  output reg  [1:0]  state);	// Current state of the FSM


/* - - - - - - - - - - - - - - - - - - - - - - - - - - - - - - - - - - - - - -*/
/* Declarations of any internal signals and buses used                        */

reg [1:0] current_state, next_state;

/* - - - - - - - - - - - - - - - - - - - - - - - - - - - - - - - - - - - - - -*/

/* - - - - - - - - - - - - - - - - - - - - - - - - - - - - - - - - - - - - - -*/
/* FSM here                                                                   */

/* Next state logic */
always @ (*)

    case (current_state)

        `FETCH:      next_state = `EXECUTE;

        `EXECUTE:    if (opcode == `LDST)   next_state = `MEMORY;
                     else                   next_state = `FETCH;

        `MEMORY:     next_state = `FETCH;

        default:     next_state = 2'bxx;

    endcase

/* Reset and change memory logic */
always @ (posedge clk, posedge rst)
    begin
        if (rst)
            current_state <= `FETCH;
        else
            current_state <= next_state;
    end
    
/* Output logic logic */
always @ (*)
    begin
        state = current_state;
    end


/* - - - - - - - - - - - - - - - - - - - - - - - - - - - - - - - - - - - - - -*/


/*----------------------------------------------------------------------------*/

endmodule

// for simulation purposes, do not delete
`default_nettype wire

/*============================================================================*/

Exercise4/Stump_FSM_tb.v
// Stump FSM testbench
// Horia-Gabriel Radu (based on a design by (P W Nutter (based on a design by Jeff Pepper))
// Nov 2020
// 

// Do not touch the following line it is required for simulation 
`timescale 1ns/100ps 

// module header

module Stump_FSM_tb();

// Internal connections

reg  clk, rst;
reg  [2:0] opcode;
wire [1:0] state;

// Instantiate mu0 fsm as dut (device under test)

Stump_FSM U0 (
    .clk    (clk),
    .rst    (rst),
    .opcode (opcode),
    .state  (state)
);

// Set up the clock

initial clk = 0;
initial rst = 0;
initial opcode = 0;

always
    begin
        #50 clk = ~clk;
    end
    

// Test vectors
initial
    begin
        // First we test all the instructions except LD/ST
        rst = 1;
        #5
        rst = 0;
        opcode = 0;
        #195
        rst = 1;
        #5
        rst = 0;
        opcode = 1;
        #195
        rst = 1;
        #5
        rst = 0;
        opcode = 2;
        #195
        rst = 1;
        #5
        rst = 0;
        opcode = 3;
        #195
        rst = 1;
        #5
        rst = 0;
        opcode = 4;
        #195
        rst = 1;
        #5
        rst = 0;
        opcode = 5;
        #195
        rst = 1;
        #5
        rst = 0;
        opcode = 7;
        #195

        // Then we test the LD/ST instruction together with the reset signal

        // Tests for reset in first state for LD/ST
        #50
        rst = 1;
        opcode = 6;
        #5
        rst = 0;
        #95
        rst = 1;
        #5
        rst = 0;

        // Tests for reset in second state for LD/ST
        #145
        rst = 1;
        #5
        rst = 0;

        // Tests for reset in third state for LD/ST
        #195
        rst = 1;
        #5
        rst = 0;

        // And test for the whole sequence
        #450

        #100 $finish; // exit the simulation
    end
 
// Save results as VCD file 
initial
 begin
  $dumpfile("Stump_FSM_tb_results.vcd");  // Save simulation waveforms in this file
  $dumpvars; // Capture all simulation waveforms
 end

endmodule

Exercise3/Stump_FSM_tb_results.vcd
$date
	Fri Dec  4 15:13:19 2020
$end
$version
	Icarus Verilog
$end
$timescale
	100ps
$end
$scope module Stump_FSM_tb $end
$var wire 2 ! state [1:0] $end
$var reg 1 " clk $end
$var reg 3 # opcode [2:0] $end
$var reg 1 $ rst $end
$scope module U0 $end
$var wire 1 " clk $end
$var wire 3 % opcode [2:0] $end
$var wire 1 $ rst $end
$var reg 2 & current_state [1:0] $end
$var reg 2 ' next_state [1:0] $end
$var reg 2 ( state [1:0] $end
$upscope $end
$upscope $end
$enddefinitions $end
#0
$dumpvars
b0 (
b1 '
b0 &
b0 %
1$
b0 #
0"
b0 !
$end
#50
0$
#500
b1 !
b1 (
b0 '
b1 &
1"
#1000
0"
#1500
b0 !
b0 (
b1 '
b0 &
1"
#2000
0"
1$
#2050
b1 #
b1 %
0$
#2500
b1 !
b1 (
b0 '
b1 &
1"
#3000
0"
#3500
b0 !
b0 (
b1 '
b0 &
1"
#4000
0"
1$
#4050
b10 #
b10 %
0$
#4500
b1 !
b1 (
b0 '
b1 &
1"
#5000
0"
#5500
b0 !
b0 (
b1 '
b0 &
1"
#6000
0"
1$
#6050
b11 #
b11 %
0$
#6500
b1 !
b1 (
b0 '
b1 &
1"
#7000
0"
#7500
b0 !
b0 (
b1 '
b0 &
1"
#8000
0"
1$
#8050
b100 #
b100 %
0$
#8500
b1 !
b1 (
b0 '
b1 &
1"
#9000
0"
#9500
b0 !
b0 (
b1 '
b0 &
1"
#10000
0"
1$
#10050
b101 #
b101 %
0$
#10500
b1 !
b1 (
b0 '
b1 &
1"
#11000
0"
#11500
b0 !
b0 (
b1 '
b0 &
1"
#12000
0"
1$
#12050
b111 #
b111 %
0$
#12500
b1 !
b1 (
b0 '
b1 &
1"
#13000
0"
#13500
b0 !
b0 (
b1 '
b0 &
1"
#14000
0"
#14500
1"
b110 #
b110 %
1$
#14550
0$
#15000
0"
#15500
1"
1$
#15550
0$
#16000
0"
#16500
b1 !
b1 (
b10 '
b1 &
1"
#17000
b0 !
b0 (
b1 '
b0 &
0"
1$
#17050
0$
#17500
b1 !
b1 (
b10 '
b1 &
1"
#18000
0"
#18500
b10 !
b10 (
b0 '
b10 &
1"
#19000
b0 !
b0 (
b1 '
b0 &
0"
1$
#19050
0$
#19500
b1 !
b1 (
b10 '
b1 &
1"
#20000
0"
#20500
b10 !
b10 (
b0 '
b10 &
1"
#21000
0"
#21500
b0 !
b0 (
b1 '
b0 &
1"
#22000
0"
#22500
b1 !
b1 (
b10 '
b1 &
1"
#23000
0"
#23500
b10 !
b10 (
b0 '
b10 &
1"
#24000
0"
#24500
b0 !
b0 (
b1 '
b0 &
1"
